{
    "characterName": "Chica the Chicken",
    "shortCharacterName": "Chica",
    "pronouns": "She/Her",
    "description": "",
    "decadeMade": 1970,
    "yearMade": -1,
    "estimatedYear": true,
    "isBorn": false,
    "yearDied": -1,
    "reasonOfDeath": "",
    "familyMembers": [],
    "owners": [],
    "locations": [],
    "occupation": "",
    "employment": [],
    "affiliation": [],
    "aliases": [],
    "animClass": "",
    "model": "",
    "height": -1,
    "weight": -1,
    "mainColor": "",
    "secondaryColor": "",
    "eyeColor": "",
    "clothes": [],
    "teethType": "",
    "armCount": -1,
    "legCount": -1,
    "state": "",
    "hasKilled": "",
    "firstAppearance": "",
    "majorAppearances": [],
    "minorAppearances": [],
    "cameos": [],
    "voiceActor": "",
    "voicelinePaths": [],
    "polaroidsPaths": [
        "Polaroids/Polaroid0"
    ],
    "imagesPaths": [
        "Images/Image0",
        "Images/Image1",
        "Images/Image2",
        "Images/Image3",
        "Images/Image4",
        "Images/Image5",
        "Images/Image6",
        "Images/Image7"
    ]
}